moldudp/__init__.py
moldudp/codec/__init__.py
moldudp/codec/const.py
moldudp/codec/decoder.py
moldudp/codec/encoder.py
moldudp/msg/__init__.py
moldudp/msg/msgpub.py
moldudp/msg/msgsub.py
moldudp/store/__init__.py
moldudp/store/bf_store.py
moldudp/store/mm_store.py
moldudp/store/store.py
moldudp-0.0.21.dist-info/LICENSE
moldudp-0.0.21.dist-info/METADATA
moldudp-0.0.21.dist-info/WHEEL
moldudp-0.0.21.dist-info/top_level.txt
moldudp-0.0.21.dist-info/RECORD
