Metadata-Version: 2.1
Name: moldudp
Version: 0.0.21
Summary: A simple library to decode/encode MoldUDP64 bytearray/packet
Home-page: https://github.com/cchee/moldudp
Author: Chester Chee
Author-email: chester.chee@gmail.com
License: Copyright (c) 2018 The Python Packaging Authority
